wfrfmodel/RF_1748260280.629787.txt
wfrfmodel/__init__.py
wfrfmodel/_version.py
wfrfmodel/main.py
wfrfmodel/scaler.json
wfrfmodel/atomic_features/firstionizationenergy.txt
wfrfmodel/atomic_features/mendeleev.txt
wfrfmodel-2.3.3.dist-info/licenses/LICENSE.md
wfrfmodel-2.3.3.dist-info/METADATA
wfrfmodel-2.3.3.dist-info/WHEEL
wfrfmodel-2.3.3.dist-info/top_level.txt
wfrfmodel-2.3.3.dist-info/RECORD
