Metadata-Version: 2.4
Name: wfrfmodel
Version: 2.3.3
Summary: Random Forest Model to predict the work function of surfaces
Author-email: Peter Schindler <p.schindler@northeastern.edu>
Maintainer-email: Peter Schindler <p.schindler@northeastern.edu>
License: MIT License
Project-URL: Repository, https://github.com/d2r2group/WF-RF-Model
Keywords: machine learning,materials science,work function,random forest
Classifier: Programming Language :: Python
Classifier: Programming Language :: Python :: 3.10
Classifier: Programming Language :: Python :: 3.11
Classifier: Programming Language :: Python :: 3.12
Classifier: Intended Audience :: Science/Research
Classifier: Topic :: Scientific/Engineering
Classifier: Operating System :: Microsoft :: Windows
Classifier: Operating System :: Unix
Classifier: Operating System :: MacOS
Classifier: License :: OSI Approved :: MIT License
Requires-Python: >=3.10
License-File: LICENSE.md
Requires-Dist: joblib>=1.5.1
Requires-Dist: numpy>=2.2.6
Requires-Dist: pandas>=2.2.3
Requires-Dist: pathlib>=1.0.1
Requires-Dist: pymatgen>=2025.5.2
Requires-Dist: scikit-learn>=1.6.1
Dynamic: license-file
